pyxboxcontroller/XInput.py
pyxboxcontroller/__init__.py
pyxboxcontroller/controller.py
pyxboxcontroller/examples/__init__.py
pyxboxcontroller/examples/example_print_state.py
pyxboxcontroller/examples/example_state_gui.py
pyxboxcontroller-0.7.3.dist-info/LICENCE
pyxboxcontroller-0.7.3.dist-info/METADATA
pyxboxcontroller-0.7.3.dist-info/WHEEL
pyxboxcontroller-0.7.3.dist-info/top_level.txt
pyxboxcontroller-0.7.3.dist-info/RECORD
