Metadata-Version: 2.1
Name: pyxboxcontroller
Version: 0.7.3
Summary: Allows simple access to the current state of connected Xbox controllers on Windows.
Home-page: https://github.com/SimpleHydrogen/pyxboxcontroller
Author: Dan Forbes
Author-email: danielforbes.123412@gmail.com
License: MIT
Keywords: xbox controller,XInput,xbox,controller,python,xbox-controller,xboxcontroller
Classifier: Programming Language :: Python :: 3.11
Classifier: License :: OSI Approved :: MIT License
Classifier: Operating System :: Microsoft :: Windows :: Windows 11
License-File: LICENCE
